toastcord/__init__.py
toastcord-0.0.1a0.dist-info/LICENSE.md
toastcord-0.0.1a0.dist-info/WHEEL
toastcord-0.0.1a0.dist-info/METADATA
toastcord-0.0.1a0.dist-info/RECORD
