Metadata-Version: 2.1
Name: toastcord
Version: 0.0.1a0
Summary: Collection of useful utilities for discord.py (and maybe Hikari :P)
Home-page: UNKNOWN
License: LGPL-3.0
Author: Tmpod
Author-email: tmpod@protonmail.com
Requires-Python: >=3.7,<4.0
Classifier: License :: OSI Approved :: GNU Lesser General Public License v3 (LGPLv3)
Classifier: Programming Language :: Python :: 3
Classifier: Programming Language :: Python :: 3.7
